MANIFEST.in
README.rst
setup.py
zype/__init__.py
zype/request.py
zype/resource.py
zype/zype.py
zype.egg-info/PKG-INFO
zype.egg-info/SOURCES.txt
zype.egg-info/dependency_links.txt
zype.egg-info/not-zip-safe
zype.egg-info/requires.txt
zype.egg-info/top_level.txt