Metadata-Version: 1.1
Name: zype
Version: 0.1.0
Summary: Zype API Python Client
Home-page: http://github.com/khfayzullaev/zype-python
Author: Khurshid Fayzullaev
Author-email: khurshidfayzullaev@yahoo.com
License: Apache License 2.0
Keywords: zype api client
Platform: UNKNOWN
Classifier: Development Status :: 2 - Pre-Alpha
Classifier: Intended Audience :: Developers
Classifier: License :: OSI Approved :: Apache Software License
Classifier: Programming Language :: Python :: 2.7
Classifier: Topic :: Software Development :: Libraries :: Python Modules
